libpysendmail.py
pysendmail
setup.py
pysendmail.egg-info/PKG-INFO
pysendmail.egg-info/SOURCES.txt
pysendmail.egg-info/dependency_links.txt
pysendmail.egg-info/not-zip-safe
pysendmail.egg-info/top_level.txt