Metadata-Version: 1.0
Name: pysendmail
Version: 1.3.0
Summary: Send email from BASH via Python
Home-page: https://github.com/ondrejsika/pysendmail/
Author: Ondrej Sika
Author-email: ondrej@ondrejsika.com
License: MIT
Platform: UNKNOWN
